setup.py
libraarby/__init__.py
libraarby/libraarby.py
libraarby.egg-info/PKG-INFO
libraarby.egg-info/SOURCES.txt
libraarby.egg-info/dependency_links.txt
libraarby.egg-info/top_level.txt