Metadata-Version: 2.1
Name: libraarby
Version: 0.1.0
Summary: less typing
Author: mishalol
Author-email: misha5335758@gmail.com
Classifier: Development Status :: 1 - Planning
Classifier: Intended Audience :: Developers
Classifier: Programming Language :: Python :: 3
Classifier: Operating System :: Unix
Classifier: Operating System :: MacOS :: MacOS X
Classifier: Operating System :: Microsoft :: Windows
